<?xml version="1.0" ?>
<MovieCDStore>
    <Category_Classical>
        <Movie1>
            <MovieTitle> Devdas</MovieTitle>
            <ActorName>Shahrukh Khan </ActorName>
            <ReleaseYear> 2004</ReleaseYear>
        </Movie1>
    </Category_Classical>

    <Category_Horror>
        <Movie2>
            <MovieTitle> Laxmii</MovieTitle>
            <ActorName> Akshay Kumar</ActorName>
            <ReleaseYear> 2016</ReleaseYear>
        </Movie2>
    </Category_Horror>

    <Category_Action>
        <Movie3>
            <MovieTitle> War</MovieTitle>
            <ActorName> Tiger Shroff</ActorName>
            <releaseYear> 2019</releaseYear>
        </Movie3>
    </Category_Action>
</MovieCDStore>
